README.rst
setup.py
django_fakeauth/__init__.py
django_fakeauth.egg-info/PKG-INFO
django_fakeauth.egg-info/SOURCES.txt
django_fakeauth.egg-info/dependency_links.txt
django_fakeauth.egg-info/not-zip-safe
django_fakeauth.egg-info/top_level.txt