Metadata-Version: 1.1
Name: django-fakeauth
Version: 0.1
Summary: A fake authentication backend for django
Home-page: UNKNOWN
Author: Mozilla Foundation & contributors
Author-email: services-dev@lists.mozila.org
License: UNKNOWN
Platform: UNKNOWN
Classifier: Programming Language :: Python
Classifier: License :: OSI Approved :: Apache Software License
Classifier: Development Status :: 1 - Planning
